{"0": {"value": ["root", "Horizontal-up", [0, 0, 256, 256]], "children": [{"value": ["Horizontal-up", "leaf_node", [0, 0, 256, 158]], "children": []}, {"value": ["Horizontal-up", "Vertical-left", [0, 158, 256, 98]], "children": [{"value": ["Vertical-left", "Horizontal-up", [0, 158, 98, 98]], "children": [{"value": ["Horizontal-up", "leaf_node", [0, 158, 98, 60]], "children": []}, {"value": ["Horizontal-up", "leaf_node", [0, 218, 98, 38]], "children": []}]}, {"value": ["Vertical-left", "leaf_node", [98, 158, 158, 98]], "children": []}]}]}, "1": {"value": ["root", "Vertical-symmetry", [0, 0, 256, 256]], "children": [{"value": ["Vertical-symmetry", "leaf_node", [0, 0, 98, 256]], "children": []}, {"value": ["Vertical-symmetry", "Vertical-symmetry", [98, 0, 60, 256]], "children": [{"value": ["Vertical-symmetry", "leaf_node", [98, 0, 23, 256]], "children": []}, {"value": ["Vertical-symmetry", "leaf_node", [121, 0, 14, 256]], "children": []}, {"value": ["Vertical-symmetry", "Horizontal-symmetry", [135, 0, 23, 256]], "children": [{"value": ["Horizontal-symmetry", "leaf_node", [135, 0, 23, 98]], "children": []}, {"value": ["Horizontal-symmetry", "leaf_node", [135, 98, 23, 60]], "children": []}, {"value": ["Horizontal-symmetry", "leaf_node", [135, 158, 23, 98]], "children": []}]}]}, {"value": ["Vertical-symmetry", "Vertical-right", [158, 0, 98, 256]], "children": [{"value": ["Vertical-right", "leaf_node", [158, 0, 60, 256]], "children": []}, {"value": ["Vertical-right", "Horizontal-up", [218, 0, 38, 256]], "children": [{"value": ["Horizontal-up", "leaf_node", [218, 0, 38, 158]], "children": []}, {"value": ["Horizontal-up", "leaf_node", [218, 158, 38, 98]], "children": []}]}]}]}, "2": {"value": ["root", "Horizontal-down", [0, 0, 256, 256]], "children": [{"value": ["Horizontal-down", "Vertical-right", [0, 0, 256, 98]], "children": [{"value": ["Vertical-right", "Horizontal-up", [0, 0, 158, 98]], "children": [{"value": ["Horizontal-up", "leaf_node", [0, 0, 158, 60]], "children": []}, {"value": ["Horizontal-up", "leaf_node", [0, 60, 158, 38]], "children": []}]}, {"value": ["Vertical-right", "Horizontal-symmetry", [158, 0, 98, 98]], "children": [{"value": ["Horizontal-symmetry", "leaf_node", [158, 0, 98, 38]], "children": []}, {"value": ["Horizontal-symmetry", "leaf_node", [158, 38, 98, 22]], "children": []}, {"value": ["Horizontal-symmetry", "leaf_node", [158, 60, 98, 38]], "children": []}]}]}, {"value": ["Horizontal-down", "Vertical-right", [0, 98, 256, 158]], "children": [{"value": ["Vertical-right", "Horizontal-down", [0, 98, 158, 158]], "children": [{"value": ["Horizontal-down", "leaf_node", [0, 98, 158, 61]], "children": []}, {"value": ["Horizontal-down", "leaf_node", [0, 159, 158, 97]], "children": []}]}, {"value": ["Vertical-right", "Horizontal-symmetry", [158, 98, 98, 158]], "children": [{"value": ["Horizontal-symmetry", "leaf_node", [158, 98, 98, 61]], "children": []}, {"value": ["Horizontal-symmetry", "leaf_node", [158, 159, 98, 36]], "children": []}, {"value": ["Horizontal-symmetry", "leaf_node", [158, 195, 98, 61]], "children": []}]}]}]}, "3": {"value": ["root", "Vertical-left", [0, 0, 256, 256]], "children": [{"value": ["Vertical-left", "Horizontal-up", [0, 0, 98, 256]], "children": [{"value": ["Horizontal-up", "Vertical-symmetry", [0, 0, 98, 158]], "children": [{"value": ["Vertical-symmetry", "leaf_node", [0, 0, 38, 158]], "children": []}, {"value": ["Vertical-symmetry", "leaf_node", [38, 0, 22, 158]], "children": []}, {"value": ["Vertical-symmetry", "leaf_node", [60, 0, 38, 158]], "children": []}]}, {"value": ["Horizontal-up", "Vertical-symmetry", [0, 158, 98, 98]], "children": [{"value": ["Vertical-symmetry", "leaf_node", [0, 158, 38, 98]], "children": []}, {"value": ["Vertical-symmetry", "leaf_node", [38, 158, 22, 98]], "children": []}, {"value": ["Vertical-symmetry", "leaf_node", [60, 158, 38, 98]], "children": []}]}]}, {"value": ["Vertical-left", "leaf_node", [98, 0, 158, 256]], "children": []}]}, "4": {"value": ["root", "Vertical-right", [0, 0, 256, 256]], "children": [{"value": ["Vertical-right", "Horizontal-symmetry", [0, 0, 158, 256]], "children": [{"value": ["Horizontal-symmetry", "leaf_node", [0, 0, 158, 98]], "children": []}, {"value": ["Horizontal-symmetry", "Vertical-left", [0, 98, 158, 60]], "children": [{"value": ["Vertical-left", "leaf_node", [0, 98, 61, 60]], "children": []}, {"value": ["Vertical-left", "leaf_node", [61, 98, 97, 60]], "children": []}]}, {"value": ["Horizontal-symmetry", "leaf_node", [0, 158, 158, 98]], "children": []}]}, {"value": ["Vertical-right", "Vertical-left", [158, 0, 98, 256]], "children": [{"value": ["Vertical-left", "Vertical-symmetry", [158, 0, 38, 256]], "children": [{"value": ["Vertical-symmetry", "leaf_node", [158, 0, 15, 256]], "children": []}, {"value": ["Vertical-symmetry", "leaf_node", [173, 0, 8, 256]], "children": []}, {"value": ["Vertical-symmetry", "leaf_node", [181, 0, 15, 256]], "children": []}]}, {"value": ["Vertical-left", "Vertical-right", [196, 0, 60, 256]], "children": [{"value": ["Vertical-right", "leaf_node", [196, 0, 37, 256]], "children": []}, {"value": ["Vertical-right", "leaf_node", [233, 0, 23, 256]], "children": []}]}]}]}, "5": {"value": ["root", "Horizontal-down", [0, 0, 256, 256]], "children": [{"value": ["Horizontal-down", "Vertical-symmetry", [0, 0, 256, 98]], "children": [{"value": ["Vertical-symmetry", "Horizontal-symmetry", [0, 0, 98, 98]], "children": [{"value": ["Horizontal-symmetry", "leaf_node", [0, 0, 98, 38]], "children": []}, {"value": ["Horizontal-symmetry", "leaf_node", [0, 38, 98, 22]], "children": []}, {"value": ["Horizontal-symmetry", "leaf_node", [0, 60, 98, 38]], "children": []}]}, {"value": ["Vertical-symmetry", "Vertical-left", [98, 0, 60, 98]], "children": [{"value": ["Vertical-left", "leaf_node", [98, 0, 23, 98]], "children": []}, {"value": ["Vertical-left", "leaf_node", [121, 0, 37, 98]], "children": []}]}, {"value": ["Vertical-symmetry", "Vertical-left", [158, 0, 98, 98]], "children": [{"value": ["Vertical-left", "leaf_node", [158, 0, 38, 98]], "children": []}, {"value": ["Vertical-left", "leaf_node", [196, 0, 60, 98]], "children": []}]}]}, {"value": ["Horizontal-down", "Vertical-left", [0, 98, 256, 158]], "children": [{"value": ["Vertical-left", "Vertical-symmetry", [0, 98, 98, 158]], "children": [{"value": ["Vertical-symmetry", "leaf_node", [0, 98, 38, 158]], "children": []}, {"value": ["Vertical-symmetry", "leaf_node", [38, 98, 22, 158]], "children": []}, {"value": ["Vertical-symmetry", "leaf_node", [60, 98, 38, 158]], "children": []}]}, {"value": ["Vertical-left", "Horizontal-down", [98, 98, 158, 158]], "children": [{"value": ["Horizontal-down", "leaf_node", [98, 98, 158, 61]], "children": []}, {"value": ["Horizontal-down", "leaf_node", [98, 159, 158, 97]], "children": []}]}]}]}, "6": {"value": ["root", "Vertical-symmetry", [0, 0, 256, 256]], "children": [{"value": ["Vertical-symmetry", "Vertical-left", [0, 0, 98, 256]], "children": [{"value": ["Vertical-left", "Horizontal-symmetry", [0, 0, 38, 256]], "children": [{"value": ["Horizontal-symmetry", "leaf_node", [0, 0, 38, 98]], "children": []}, {"value": ["Horizontal-symmetry", "leaf_node", [0, 98, 38, 60]], "children": []}, {"value": ["Horizontal-symmetry", "leaf_node", [0, 158, 38, 98]], "children": []}]}, {"value": ["Vertical-left", "Horizontal-down", [38, 0, 60, 256]], "children": [{"value": ["Horizontal-down", "leaf_node", [38, 0, 60, 98]], "children": []}, {"value": ["Horizontal-down", "leaf_node", [38, 98, 60, 158]], "children": []}]}]}, {"value": ["Vertical-symmetry", "Vertical-symmetry", [98, 0, 60, 256]], "children": [{"value": ["Vertical-symmetry", "Horizontal-up", [98, 0, 23, 256]], "children": [{"value": ["Horizontal-up", "leaf_node", [98, 0, 23, 158]], "children": []}, {"value": ["Horizontal-up", "leaf_node", [98, 158, 23, 98]], "children": []}]}, {"value": ["Vertical-symmetry", "Vertical-right", [121, 0, 14, 256]], "children": [{"value": ["Vertical-right", "leaf_node", [121, 0, 8, 256]], "children": []}, {"value": ["Vertical-right", "leaf_node", [129, 0, 6, 256]], "children": []}]}, {"value": ["Vertical-symmetry", "leaf_node", [135, 0, 23, 256]], "children": []}]}, {"value": ["Vertical-symmetry", "leaf_node", [158, 0, 98, 256]], "children": []}]}, "7": {"value": ["root", "Vertical-right", [0, 0, 256, 256]], "children": [{"value": ["Vertical-right", "leaf_node", [0, 0, 158, 256]], "children": []}, {"value": ["Vertical-right", "leaf_node", [158, 0, 98, 256]], "children": []}]}, "8": {"value": ["root", "Vertical-symmetry", [0, 0, 256, 256]], "children": [{"value": ["Vertical-symmetry", "Horizontal-symmetry", [0, 0, 98, 256]], "children": [{"value": ["Horizontal-symmetry", "leaf_node", [0, 0, 98, 98]], "children": []}, {"value": ["Horizontal-symmetry", "leaf_node", [0, 98, 98, 60]], "children": []}, {"value": ["Horizontal-symmetry", "leaf_node", [0, 158, 98, 98]], "children": []}]}, {"value": ["Vertical-symmetry", "leaf_node", [98, 0, 60, 256]], "children": []}, {"value": ["Vertical-symmetry", "Vertical-left", [158, 0, 98, 256]], "children": [{"value": ["Vertical-left", "Vertical-symmetry", [158, 0, 38, 256]], "children": [{"value": ["Vertical-symmetry", "leaf_node", [158, 0, 15, 256]], "children": []}, {"value": ["Vertical-symmetry", "leaf_node", [173, 0, 8, 256]], "children": []}, {"value": ["Vertical-symmetry", "leaf_node", [181, 0, 15, 256]], "children": []}]}, {"value": ["Vertical-left", "Horizontal-down", [196, 0, 60, 256]], "children": [{"value": ["Horizontal-down", "leaf_node", [196, 0, 60, 98]], "children": []}, {"value": ["Horizontal-down", "leaf_node", [196, 98, 60, 158]], "children": []}]}]}]}, "9": {"value": ["root", "Vertical-left", [0, 0, 256, 256]], "children": [{"value": ["Vertical-left", "Vertical-left", [0, 0, 98, 256]], "children": [{"value": ["Vertical-left", "Vertical-symmetry", [0, 0, 38, 256]], "children": [{"value": ["Vertical-symmetry", "leaf_node", [0, 0, 15, 256]], "children": []}, {"value": ["Vertical-symmetry", "leaf_node", [15, 0, 8, 256]], "children": []}, {"value": ["Vertical-symmetry", "leaf_node", [23, 0, 15, 256]], "children": []}]}, {"value": ["Vertical-left", "Horizontal-up", [38, 0, 60, 256]], "children": [{"value": ["Horizontal-up", "leaf_node", [38, 0, 60, 158]], "children": []}, {"value": ["Horizontal-up", "leaf_node", [38, 158, 60, 98]], "children": []}]}]}, {"value": ["Vertical-left", "Vertical-symmetry", [98, 0, 158, 256]], "children": [{"value": ["Vertical-symmetry", "leaf_node", [98, 0, 61, 256]], "children": []}, {"value": ["Vertical-symmetry", "Vertical-right", [159, 0, 36, 256]], "children": [{"value": ["Vertical-right", "leaf_node", [159, 0, 22, 256]], "children": []}, {"value": ["Vertical-right", "leaf_node", [181, 0, 14, 256]], "children": []}]}, {"value": ["Vertical-symmetry", "leaf_node", [195, 0, 61, 256]], "children": []}]}]}, "10": {"value": ["root", "Horizontal-up", [0, 0, 256, 256]], "children": [{"value": ["Horizontal-up", "Vertical-left", [0, 0, 256, 158]], "children": [{"value": ["Vertical-left", "leaf_node", [0, 0, 98, 158]], "children": []}, {"value": ["Vertical-left", "Vertical-left", [98, 0, 158, 158]], "children": [{"value": ["Vertical-left", "leaf_node", [98, 0, 61, 158]], "children": []}, {"value": ["Vertical-left", "leaf_node", [159, 0, 97, 158]], "children": []}]}]}, {"value": ["Horizontal-up", "Vertical-right", [0, 158, 256, 98]], "children": [{"value": ["Vertical-right", "Vertical-symmetry", [0, 158, 158, 98]], "children": [{"value": ["Vertical-symmetry", "leaf_node", [0, 158, 61, 98]], "children": []}, {"value": ["Vertical-symmetry", "leaf_node", [61, 158, 36, 98]], "children": []}, {"value": ["Vertical-symmetry", "leaf_node", [97, 158, 61, 98]], "children": []}]}, {"value": ["Vertical-right", "Horizontal-up", [158, 158, 98, 98]], "children": [{"value": ["Horizontal-up", "leaf_node", [158, 158, 98, 60]], "children": []}, {"value": ["Horizontal-up", "leaf_node", [158, 218, 98, 38]], "children": []}]}]}]}, "11": {"value": ["root", "Horizontal-up", [0, 0, 256, 256]], "children": [{"value": ["Horizontal-up", "Vertical-symmetry", [0, 0, 256, 158]], "children": [{"value": ["Vertical-symmetry", "Vertical-right", [0, 0, 98, 158]], "children": [{"value": ["Vertical-right", "leaf_node", [0, 0, 60, 158]], "children": []}, {"value": ["Vertical-right", "leaf_node", [60, 0, 38, 158]], "children": []}]}, {"value": ["Vertical-symmetry", "Horizontal-symmetry", [98, 0, 60, 158]], "children": [{"value": ["Horizontal-symmetry", "leaf_node", [98, 0, 60, 61]], "children": []}, {"value": ["Horizontal-symmetry", "leaf_node", [98, 61, 60, 36]], "children": []}, {"value": ["Horizontal-symmetry", "leaf_node", [98, 97, 60, 61]], "children": []}]}, {"value": ["Vertical-symmetry", "leaf_node", [158, 0, 98, 158]], "children": []}]}, {"value": ["Horizontal-up", "Vertical-left", [0, 158, 256, 98]], "children": [{"value": ["Vertical-left", "Horizontal-up", [0, 158, 98, 98]], "children": [{"value": ["Horizontal-up", "leaf_node", [0, 158, 98, 60]], "children": []}, {"value": ["Horizontal-up", "leaf_node", [0, 218, 98, 38]], "children": []}]}, {"value": ["Vertical-left", "Vertical-symmetry", [98, 158, 158, 98]], "children": [{"value": ["Vertical-symmetry", "leaf_node", [98, 158, 61, 98]], "children": []}, {"value": ["Vertical-symmetry", "leaf_node", [159, 158, 36, 98]], "children": []}, {"value": ["Vertical-symmetry", "leaf_node", [195, 158, 61, 98]], "children": []}]}]}]}, "12": {"value": ["root", "Horizontal-up", [0, 0, 256, 256]], "children": [{"value": ["Horizontal-up", "Horizontal-symmetry", [0, 0, 256, 158]], "children": [{"value": ["Horizontal-symmetry", "Vertical-left", [0, 0, 256, 61]], "children": [{"value": ["Vertical-left", "leaf_node", [0, 0, 98, 61]], "children": []}, {"value": ["Vertical-left", "leaf_node", [98, 0, 158, 61]], "children": []}]}, {"value": ["Horizontal-symmetry", "Vertical-right", [0, 61, 256, 36]], "children": [{"value": ["Vertical-right", "leaf_node", [0, 61, 158, 36]], "children": []}, {"value": ["Vertical-right", "leaf_node", [158, 61, 98, 36]], "children": []}]}, {"value": ["Horizontal-symmetry", "leaf_node", [0, 97, 256, 61]], "children": []}]}, {"value": ["Horizontal-up", "Vertical-symmetry", [0, 158, 256, 98]], "children": [{"value": ["Vertical-symmetry", "Horizontal-up", [0, 158, 98, 98]], "children": [{"value": ["Horizontal-up", "leaf_node", [0, 158, 98, 60]], "children": []}, {"value": ["Horizontal-up", "leaf_node", [0, 218, 98, 38]], "children": []}]}, {"value": ["Vertical-symmetry", "Vertical-symmetry", [98, 158, 60, 98]], "children": [{"value": ["Vertical-symmetry", "leaf_node", [98, 158, 23, 98]], "children": []}, {"value": ["Vertical-symmetry", "leaf_node", [121, 158, 14, 98]], "children": []}, {"value": ["Vertical-symmetry", "leaf_node", [135, 158, 23, 98]], "children": []}]}, {"value": ["Vertical-symmetry", "leaf_node", [158, 158, 98, 98]], "children": []}]}]}, "13": {"value": ["root", "Vertical-left", [0, 0, 256, 256]], "children": [{"value": ["Vertical-left", "Horizontal-down", [0, 0, 98, 256]], "children": [{"value": ["Horizontal-down", "Vertical-right", [0, 0, 98, 98]], "children": [{"value": ["Vertical-right", "leaf_node", [0, 0, 60, 98]], "children": []}, {"value": ["Vertical-right", "leaf_node", [60, 0, 38, 98]], "children": []}]}, {"value": ["Horizontal-down", "Horizontal-down", [0, 98, 98, 158]], "children": [{"value": ["Horizontal-down", "leaf_node", [0, 98, 98, 61]], "children": []}, {"value": ["Horizontal-down", "leaf_node", [0, 159, 98, 97]], "children": []}]}]}, {"value": ["Vertical-left", "leaf_node", [98, 0, 158, 256]], "children": []}]}, "14": {"value": ["root", "Horizontal-down", [0, 0, 256, 256]], "children": [{"value": ["Horizontal-down", "Vertical-symmetry", [0, 0, 256, 98]], "children": [{"value": ["Vertical-symmetry", "Vertical-symmetry", [0, 0, 98, 98]], "children": [{"value": ["Vertical-symmetry", "leaf_node", [0, 0, 38, 98]], "children": []}, {"value": ["Vertical-symmetry", "leaf_node", [38, 0, 22, 98]], "children": []}, {"value": ["Vertical-symmetry", "leaf_node", [60, 0, 38, 98]], "children": []}]}, {"value": ["Vertical-symmetry", "leaf_node", [98, 0, 60, 98]], "children": []}, {"value": ["Vertical-symmetry", "Vertical-symmetry", [158, 0, 98, 98]], "children": [{"value": ["Vertical-symmetry", "leaf_node", [158, 0, 38, 98]], "children": []}, {"value": ["Vertical-symmetry", "leaf_node", [196, 0, 22, 98]], "children": []}, {"value": ["Vertical-symmetry", "leaf_node", [218, 0, 38, 98]], "children": []}]}]}, {"value": ["Horizontal-down", "leaf_node", [0, 98, 256, 158]], "children": []}]}, "15": {"value": ["root", "Vertical-symmetry", [0, 0, 256, 256]], "children": [{"value": ["Vertical-symmetry", "leaf_node", [0, 0, 98, 256]], "children": []}, {"value": ["Vertical-symmetry", "Vertical-symmetry", [98, 0, 60, 256]], "children": [{"value": ["Vertical-symmetry", "Horizontal-down", [98, 0, 23, 256]], "children": [{"value": ["Horizontal-down", "leaf_node", [98, 0, 23, 98]], "children": []}, {"value": ["Horizontal-down", "leaf_node", [98, 98, 23, 158]], "children": []}]}, {"value": ["Vertical-symmetry", "leaf_node", [121, 0, 14, 256]], "children": []}, {"value": ["Vertical-symmetry", "Vertical-right", [135, 0, 23, 256]], "children": [{"value": ["Vertical-right", "leaf_node", [135, 0, 14, 256]], "children": []}, {"value": ["Vertical-right", "leaf_node", [149, 0, 9, 256]], "children": []}]}]}, {"value": ["Vertical-symmetry", "Horizontal-symmetry", [158, 0, 98, 256]], "children": [{"value": ["Horizontal-symmetry", "Vertical-left", [158, 0, 98, 98]], "children": [{"value": ["Vertical-left", "leaf_node", [158, 0, 38, 98]], "children": []}, {"value": ["Vertical-left", "leaf_node", [196, 0, 60, 98]], "children": []}]}, {"value": ["Horizontal-symmetry", "Horizontal-up", [158, 98, 98, 60]], "children": [{"value": ["Horizontal-up", "leaf_node", [158, 98, 98, 37]], "children": []}, {"value": ["Horizontal-up", "leaf_node", [158, 135, 98, 23]], "children": []}]}, {"value": ["Horizontal-symmetry", "Horizontal-symmetry", [158, 158, 98, 98]], "children": [{"value": ["Horizontal-symmetry", "leaf_node", [158, 158, 98, 38]], "children": []}, {"value": ["Horizontal-symmetry", "leaf_node", [158, 196, 98, 22]], "children": []}, {"value": ["Horizontal-symmetry", "leaf_node", [158, 218, 98, 38]], "children": []}]}]}]}}